pyimclsts/__init__.py
pyimclsts/_base.py
pyimclsts/core.py
pyimclsts/extract.py
pyimclsts/extractutils.py
pyimclsts/network.py
pyimclsts-0.1.2.1.dist-info/METADATA
pyimclsts-0.1.2.1.dist-info/WHEEL
pyimclsts-0.1.2.1.dist-info/licenses/LICENSE
pyimclsts-0.1.2.1.dist-info/RECORD
