Metadata-Version: 2.1
Name: pyimclsts
Version: 0.1.2.1
Summary: Python bindings of the IMC message schema
Project-URL: Homepage, https://github.com/choiwd/pyimctrans
Project-URL: Bug Tracker, https://github.com/choiwd/pyimctrans/issues
Author: Choi Wang Dzak
License: Copyright (c) 2023 Laboratório de Sistemas e Tecnologia Subaquática
License-File: LICENSE
Keywords: IMC,IMC message protocol,LSTS
Classifier: License :: OSI Approved :: MIT License
Classifier: Operating System :: OS Independent
Classifier: Programming Language :: Python :: 3
Requires-Python: >=3.7
Requires-Dist: ifaddr~=0.2.0
Requires-Dist: ipaddress~=1.0.23
